co/verilog/Lab1/Q3/MUX2X1/MUX2X1.v
module mux_2x1(
    input A,        // Input 1
    input B,        // Input 2
    input Sel,      // Select line
    output reg Y        // Output
    //reg is a data type in Verilog that holds its value until it is explicitly updated.
);
    // Assign output based on Sel
    //assign Y = (Sel) ? B : A; //using ternary operator

    always @(*) begin
        if (Sel == 1'b0)
            Y = A;  // Select A when Sel is 0
        else
            Y = B;  // Select B when Sel is 1
    end
    /*
    always @(*) begin
    end

    note-> Ensures that the block executes every time 
           there's a change in any input signal used in the block.

    */

endmodule

co/verilog/Lab1/Q3/MUX2X1/MUX2X1_tb.v
`include "MUX2X1.v"

module tb_mux_2x1;

    reg A, B, Sel;
    wire Y;

    // Instantiate the 2x1 MUX
    mux_2x1 uut (
        .A(A),
        .B(B),
        .Sel(Sel),
        .Y(Y)
    );

    initial begin
        $dumpfile("mux_2x1_tb.vcd");  // VCD file for waveform
        $dumpvars(0, tb_mux_2x1);

        $display("2x1 MUX Truth Table:");
        $display("A B Sel | Y");
        $display("----------------");
        for (integer i = 0; i < 8; i++) begin
            {A, B, Sel} = i; // Generate all combinations
            #1;              // Wait for simulation step
            $display("%b %b   %b  | %b", A, B, Sel, Y);
        end

        $finish;
    end
endmodule

co/verilog/Lab1/Q3/MUX2X1/mux_2x1_tb.vcd
$date
	Sat Nov 23 18:50:20 2024
$end
$version
	Icarus Verilog
$end
$timescale
	1s
$end
$scope module tb_mux_2x1 $end
$var wire 1 ! Y $end
$var reg 1 " A $end
$var reg 1 # B $end
$var reg 1 $ Sel $end
$scope module uut $end
$var wire 1 " A $end
$var wire 1 # B $end
$var wire 1 $ Sel $end
$var reg 1 ! Y $end
$upscope $end
$scope begin $ivl_for_loop0 $end
$var integer 32 % i [31:0] $end
$upscope $end
$upscope $end
$enddefinitions $end
$comment Show the parameter values. $end
$dumpall
$end
#0
$dumpvars
b0 %
0$
0#
0"
0!
$end
#1
1$
b1 %
#2
1#
0$
b10 %
#3
1!
1$
b11 %
#4
1"
0#
0$
b100 %
#5
0!
1$
b101 %
#6
1!
1#
0$
b110 %
#7
1$
b111 %
#8
b1000 %
