co/verilog/proj/proj.v
module Instruction_Memory (
    input [31:0] Instruction_Address,
    output reg [31:0] Instruction
);
    //  memory to store bytes 
    reg [7:0] mem [0:127];    // 128 bytes    
    initial 
    begin 
        // Initialize all memory locations to 0 
        for (integer k = 0; k < 128; k = k + 1) 
        begin
            mem[k] = 0;   // Clear all memory bytes
        end
        
        //examples
        //lw (lw )
        //add (add $t2, $t0, $t1)
        // 0000 00 01 000 0 1001 0 101 0 000 0010 0000 
        mem[0] = 8'h01;
        mem[1] = 8'h09;
        mem[2] = 8'h50;
        mem[3] = 8'h20;
        
        //lw 
        // 100011 01011 01101 0000 0000 0000 0000
        mem[4] = 8'h8D;
        mem[5] = 8'h6D;
        mem[6] = 8'h00;
        mem[7] = 8'h00;

        //beq 
        // 0001 00 01 010 0 1011 0000 0000 0000 0100
        mem[8] = 8'h11;  // (opcode )
        mem[9] = 8'h4B;    // (rt register)
        mem[10] = 8'h00;    // (rs register)
        mem[11] = 8'h04;    // (immediate value)
        
    end

    // Instruction Fetch Logic 
    always @(*) 
    begin
        // read 4 bytes after each other to form a 32-bit instruction 
        Instruction = {mem[Instruction_Address[31:0]], mem[Instruction_Address[31:0] + 1], mem[Instruction_Address[31:0] + 2], mem[Instruction_Address[31:0] + 3]}; 
    end

endmodule

//wire or reg? or none
module RegisterFile (
    input wire clk,
    input wire write_enable,
    input wire [4:0] rs_address,
    input wire [4:0] rt_address,
    input wire [4:0] rd_address,
    input wire [31:0] rd_data,
    output wire [31:0] rs_data,
    output wire [31:0] rt_data
);
    //shelt el reset 7seit msh m7tageino idk
    reg [31:0] registers [0:31];
    initial begin
        for(integer i = 0; i < 32; i++) begin
                registers[i] = 0;
            end
        registers[8] = 32'd1;
        registers[9] = 32'd2;
    end
    assign rs_data = registers[rs_address];
    assign rt_data = registers[rt_address];
    always @(posedge clk) begin
        if (write_enable) begin
            registers[rd_address] <= rd_data;
        end
    end
endmodule

module alu (input [31:0] a, input [31:0] b, input [5:0] func_code, input [4:0] shamt, output reg [31:0] c, output zero);

assign zero = (a - b)? 0 : 1;
always @(*)begin
    case(func_code)
        6'd36: c = a&b;
        6'd37: c = a|b;
        6'd32: c = a+b;
        6'd34: c = a-b;
        6'd42: if(a<b) c = 1; else c = 0;
        default: c = 0;
    endcase
end
endmodule

module DataMemory (
    input wire clk,
    input [31:0] Instruction_Address,   // Address for read/write operation
    input [31:0] W_Data,                // Data to write to memory
    output reg [31:0] R_Data,           // Data read from memory
    input Read_M,                       // Read control signal
    input Write_M                      // Write control signal
);

    // Memory storage: 512 words
    reg [31:0] mem [0:511];    

    initial 
    begin
        // Clear memory
        for (integer k = 0; k < 512; k = k + 1) 
            mem[k] = 0;   
        mem[13] = 32'd4;
    end
    // Read/Write Logic
    always @(posedge clk) begin
        if (Read_M) begin
                // Read 32-bit word (4 bytes)
                R_Data = {mem[Instruction_Address], mem[Instruction_Address+1], mem[Instruction_Address+2], mem[Instruction_Address+3]};
        end else if (Write_M) begin
                // Write 32-bit word (4 bytes)
                mem[Instruction_Address] = W_Data[31:24];
                mem[Instruction_Address+1] = W_Data[23:16];
                mem[Instruction_Address+2] = W_Data[15:8];
                mem[Instruction_Address+3] = W_Data[7:0];
        end else begin
            R_Data = 0; // Default to 0 when no read/write
        end
    end

endmodule

//aluop sucks {missing}
module MIPS_datapath(input clk,input write_enable, write_memory, read_memory, branch);
wire [31:0] PC, incremented_PC;
wire [31:0] instruction, BTA;
wire [31:0] signextend;
wire [4:0] rs_a, rt_a, rd_a, shamt;
wire [31:0] rs_data, rt_data, rd_data, Mem_address, write_data, read_data;
wire [31:0] A, B;
wire [31:0] aluout;
wire [5:0] aluop, funct;
reg [1:0] state;
reg PC_init;
wire zero;
initial begin
PC_init = 1;
state = 0;
end
//state 0: fetch instruction
assign PC = (PC_init) ? -4 : 
((state == 2 && aluop == 6'd4 && zero) ? BTA : (state == 0) ? PC + 4 : PC);
Instruction_Memory IM (PC,instruction);
//state 1: decode instruction
assign aluop = (state == 1)? instruction[31:26] : aluop;
assign rs_a = (state == 1) ? instruction[25:21] : rs_a;
assign rt_a = (state == 1) ? instruction[20:16] : rt_a;
assign rd_a =  (state == 1) ? ((aluop == 0) ? instruction[15:11]: rt_a): rd_a;
RegisterFile RF (clk, write_enable, rs_a, rt_a, rd_a, rd_data, rs_data, rt_data);
assign funct = (state == 1) ? 
((aluop == 6'd43 || aluop == 6'd35) ? 6'd32 : 
((aluop == 6'd4) ? 6'd34 : instruction[5:0])) : funct;
assign shamt = (state == 1) ? ((aluop == 0) ? instruction[10:6] : 0) : shamt;
assign signextend = (state == 1) ? 
((aluop == 0) ? 0 : ({{16{instruction[15]}},instruction[15:0]})) : signextend;
//state 2: execute 
assign A = (state == 2) ? rs_data : A;
// assign A = rs_data;
assign B = (state == 2) ? ((aluop == 0) ? rt_data : signextend) : B;
assign BTA = (state == 2) ? (PC + signextend << 2): BTA;
alu  ALU (A, B, funct, shamt, aluout, zero);
//state 3: read/write back
assign Mem_address = (state == 3) ? aluout : Mem_address;
assign write_data = (state == 3) ? rs_data : write_data;
DataMemory DM (clk, Mem_address, write_data, read_data, read_memory, write_memory);
assign rd_data = (state == 3) ? ((aluop == 0) ? aluout : read_data ) : rd_data; 
always @(posedge clk)
case (state)
//fetch instruction
0:
begin
    //should create a new instance
    //alu(pc,4,6'd32,0,pc,zero);
    PC_init = 0;
    state = 1;
end
//decode instruction
1:
begin
    state = 2;
end
//execute instruction
2:
begin
        //beq
        //should create a new instance instead
        // BTA = pc + signextend << 2;
        // alu(address, 2, shiftfunct, ??,BTA,zero)
    // state = (aluop == 6'd4 && zero) ? 1 : 3;
    state = 3;
end
//memory write/read
3:
begin
    // case(aluop)
    //     //lw
    //     6'd35:
    //     begin
    //     end
    //     //sw
    //     6'd43:
    //     begin
    //     end
    //     //beq
    //     6'd4:
    //     begin
    //     if(zero)begin
    //         PC = BTA;
    //         state = 1;
    //     end
    //     end
    //     6'd0:
    //     begin
    //     end
    // endcase
    state = 0;
end
endcase
endmodule

co/verilog/proj/proj_tb.v
`include "proj.v"
`timescale 1ps/1ps

module MIPS_datapath_tb;

    reg clk;
    reg write_enable, write_memory, read_memory, branch;
    reg [1:0] aluop;
    // Instantiate the ALU module
    MIPS_datapath test(clk, write_enable, write_memory, read_memory, branch);

    initial begin

        $dumpfile("datapath.vcd");
        $dumpvars(0, MIPS_datapath_tb);
        //rtype signals
        write_enable = 1; write_memory = 0; read_memory = 0; branch = 0; aluop = 10; clk = 0; #1;
        for(integer i = 0; i < 6; i++)begin
        clk = 1; 
        #1;
        end
        //lw signals
        write_enable = 1; write_memory = 0; read_memory = 1; branch = 0; aluop = 00; clk = 0; #1;
        // for(integer i = 0; i < 6; i++)begin
        // clk; 
        // #1;
        // end
        //beq signals
        write_enable = 0; write_memory = 0; read_memory = 0; branch = 1; aluop = 01; clk = 0; #1;
        // for(integer i = 0; i < 6; i++)begin
        // clk++; 
        // #1;
        // end
        $finish;
    end

endmodule

co/verilog/proj/datapath.vcd
$date
	Sun Dec 22 01:06:45 2024
$end
$version
	Icarus Verilog
$end
$timescale
	1ps
$end
$scope module MIPS_datapath_tb $end
$var reg 2 ! aluop [1:0] $end
$var reg 1 " branch $end
$var reg 1 # clk $end
$var reg 1 $ read_memory $end
$var reg 1 % write_enable $end
$var reg 1 & write_memory $end
$scope module test $end
$var wire 1 " branch $end
$var wire 1 # clk $end
$var wire 1 $ read_memory $end
$var wire 1 % write_enable $end
$var wire 1 & write_memory $end
$var wire 1 ' zero $end
$var wire 32 ( write_data [31:0] $end
$var wire 32 ) signextend [31:0] $end
$var wire 5 * shamt [4:0] $end
$var wire 32 + rt_data [31:0] $end
$var wire 5 , rt_a [4:0] $end
$var wire 32 - rs_data [31:0] $end
$var wire 5 . rs_a [4:0] $end
$var wire 32 / read_data [31:0] $end
$var wire 32 0 rd_data [31:0] $end
$var wire 5 1 rd_a [4:0] $end
$var wire 32 2 instruction [31:0] $end
$var wire 6 3 funct [5:0] $end
$var wire 32 4 aluout [31:0] $end
$var wire 6 5 aluop [5:0] $end
$var wire 32 6 PC [31:0] $end
$var wire 32 7 Mem_address [31:0] $end
$var wire 32 8 BTA [31:0] $end
$var wire 32 9 B [31:0] $end
$var wire 32 : A [31:0] $end
$var reg 1 ; PC_init $end
$var reg 2 < state [1:0] $end
$scope module ALU $end
$var wire 32 = a [31:0] $end
$var wire 32 > b [31:0] $end
$var wire 6 ? func_code [5:0] $end
$var wire 5 @ shamt [4:0] $end
$var wire 1 ' zero $end
$var reg 32 A c [31:0] $end
$upscope $end
$scope module DM $end
$var wire 32 B Instruction_Address [31:0] $end
$var wire 1 $ Read_M $end
$var wire 32 C W_Data [31:0] $end
$var wire 1 & Write_M $end
$var wire 1 # clk $end
$var reg 32 D R_Data [31:0] $end
$scope begin $ivl_for_loop2 $end
$var integer 32 E k [31:0] $end
$upscope $end
$upscope $end
$scope module IM $end
$var wire 32 F Instruction_Address [31:0] $end
$var reg 32 G Instruction [31:0] $end
$scope begin $ivl_for_loop0 $end
$var integer 32 H k [31:0] $end
$upscope $end
$upscope $end
$scope module RF $end
$var wire 1 # clk $end
$var wire 5 I rd_address [4:0] $end
$var wire 32 J rd_data [31:0] $end
$var wire 5 K rs_address [4:0] $end
$var wire 32 L rs_data [31:0] $end
$var wire 5 M rt_address [4:0] $end
$var wire 32 N rt_data [31:0] $end
$var wire 1 % write_enable $end
$scope begin $ivl_for_loop1 $end
$var integer 32 O i [31:0] $end
$upscope $end
$upscope $end
$upscope $end
$scope begin $ivl_for_loop3 $end
$var integer 32 P i [31:0] $end
$upscope $end
$upscope $end
$enddefinitions $end
$comment Show the parameter values. $end
$dumpall
$end
#0
$dumpvars
bx P
b100000 O
bx N
bx M
bx L
bx K
bx J
bx I
b10000000 H
bx G
b11111111111111111111111111111100 F
b1000000000 E
bx D
bx C
bx B
bx A
bx @
bx ?
bx >
bx =
b0 <
1;
bx :
bx 9
bxzz 8
bx 7
b11111111111111111111111111111100 6
bx 5
bx 4
bx 3
bx 2
bx 1
bx 0
bx /
bx .
bx -
bx ,
bx +
bx *
bx )
bx (
x'
0&
1%
0$
0#
0"
b10 !
$end
#1
b100000 3
b100000 ?
b0 )
b0 *
b0 @
b1010 1
b1010 I
b10 +
b10 N
b1001 ,
b1001 M
b1 -
b1 L
b1000 .
b1000 K
b0 5
b1000010010101000000100000 2
b1000010010101000000100000 G
b0 6
b0 F
b0 /
b0 D
b1 <
0;
1#
b0 P
#2
b1 P
#3
b10 P
#4
b11 P
#5
b100 P
#6
b101 P
#7
0#
b0 !
1$
b110 P
#8
b1 !
1"
0$
0%
