co/verilog/p1/p1.v

module adder(input a,input b, input cin, output s, output cout);

    assign s = a ^ b ^ cin;
    assign cout = a&b | cin & (a^b);
endmodule

module multi_adder(input a0,a1,a2,a3,b0,b1,b2,b3,cin,output s0,s1,s2,s3,c3,c0,c1,c2);

    // input a0,a1,a2,a3,b0,b1,b2,b3,cin;
    // wire s0,s1,s2,s3,c0,c1,c2,c3;
    adder f1 (a0,b0,cin,s0,c0);
    adder f2 (a1,b1,c0,s1,c1);
    adder f3 (a2,b2,c1,s2,c2);
    adder f4 (a3,b3,c2,s3,c3);  
endmodule

co/verilog/p1/p1_tb.v
`include "p1.v"

module p1_tb;

reg a0,a1,a2,a3,b0,b1,b2,b3,cin;
wire s0,s1,s2,s3,c0,c1,c2,c3;
multi_adder uut(a0,a1,a2,a3,b0,b1,b2,b3,cin,s0,s1,s2,s3,c3,c0,c1,c2);
initial begin
$dumpfile("p1_test2.vcd");
$dumpvars( 0, p1_tb);
$display("t|cin|a0|b0|s0|c0|a1|b1|s1|c1|a2|b2|s2|c2|a3|b3|s3|c3");
$monitor("%0t|%b  |%b|%b|%b|%b|%b|%b|%b|%b|%b|%b|%b|%b|%b|%b|%b|%b", $time, cin,a0,b0,s0,c0,a1,b1,s1,c1,a2,b2,s2,c2,a3,b3,s3,c3);

for(integer i = 0; i<512; i++)
begin
    {a0,a1,a2,a3,b0,b1,b2,b3,cin} = i;
    #1;
end
end
endmodule

co/verilog/p1/p1_test2.vcd
$date
	Tue Dec 03 10:43:06 2024
$end
$version
	Icarus Verilog
$end
$timescale
	1s
$end
$scope module p1_tb $end
$var wire 1 ! s3 $end
$var wire 1 " s2 $end
$var wire 1 # s1 $end
$var wire 1 $ s0 $end
$var wire 1 % c3 $end
$var wire 1 & c2 $end
$var wire 1 ' c1 $end
$var wire 1 ( c0 $end
$var reg 1 ) a0 $end
$var reg 1 * a1 $end
$var reg 1 + a2 $end
$var reg 1 , a3 $end
$var reg 1 - b0 $end
$var reg 1 . b1 $end
$var reg 1 / b2 $end
$var reg 1 0 b3 $end
$var reg 1 1 cin $end
$scope module uut $end
$var wire 1 ) a0 $end
$var wire 1 * a1 $end
$var wire 1 + a2 $end
$var wire 1 , a3 $end
$var wire 1 - b0 $end
$var wire 1 . b1 $end
$var wire 1 / b2 $end
$var wire 1 0 b3 $end
$var wire 1 1 cin $end
$var wire 1 ! s3 $end
$var wire 1 " s2 $end
$var wire 1 # s1 $end
$var wire 1 $ s0 $end
$var wire 1 % c3 $end
$var wire 1 & c2 $end
$var wire 1 ' c1 $end
$var wire 1 ( c0 $end
$scope module f1 $end
$var wire 1 ) a $end
$var wire 1 - b $end
$var wire 1 1 cin $end
$var wire 1 ( cout $end
$var wire 1 $ s $end
$upscope $end
$scope module f2 $end
$var wire 1 * a $end
$var wire 1 . b $end
$var wire 1 ( cin $end
$var wire 1 ' cout $end
$var wire 1 # s $end
$upscope $end
$scope module f3 $end
$var wire 1 + a $end
$var wire 1 / b $end
$var wire 1 ' cin $end
$var wire 1 & cout $end
$var wire 1 " s $end
$upscope $end
$scope module f4 $end
$var wire 1 , a $end
$var wire 1 0 b $end
$var wire 1 & cin $end
$var wire 1 % cout $end
$var wire 1 ! s $end
$upscope $end
$upscope $end
$scope begin $ivl_for_loop0 $end
$var integer 32 2 i [31:0] $end
$upscope $end
$upscope $end
$enddefinitions $end
$comment Show the parameter values. $end
$dumpall
$end
#0
$dumpvars
b0 2
01
00
0/
0.
0-
0,
0+
0*
0)
0(
0'
0&
0%
0$
0#
0"
0!
$end
#1
1$
11
b1 2
#2
1!
0$
10
01
b10 2
#3
1$
11
b11 2
#4
1"
0!
0$
1/
00
01
b100 2
#5
1$
11
b101 2
#6
1!
0$
10
01
b110 2
#7
1$
11
b111 2
#8
1#
0"
0!
0$
1.
0/
00
01
b1000 2
#9
1$
11
b1001 2
#10
1!
0$
10
01
b1010 2
#11
1$
11
b1011 2
#12
1"
0!
0$
1/
00
01
b1100 2
#13
1$
11
b1101 2
#14
1!
0$
10
01
b1110 2
#15
1$
11
b1111 2
#16
0#
0"
0!
1$
1-
0.
0/
00
01
b10000 2
#17
1#
1(
0$
11
b10001 2
#18
0#
1!
0(
1$
10
01
b10010 2
#19
1#
1(
0$
11
b10011 2
#20
0#
1"
0!
0(
1$
1/
00
01
b10100 2
#21
1#
1(
0$
11
b10101 2
#22
0#
1!
0(
1$
10
01
b10110 2
#23
1#
1(
0$
11
b10111 2
#24
0"
0!
0(
1$
1.
0/
00
01
b11000 2
#25
1"
1'
0#
1(
0$
11
b11001 2
#26
0"
0'
1#
1!
0(
1$
10
01
b11010 2
#27
1"
1'
0#
1(
0$
11
b11011 2
#28
0'
0&
1#
1"
0!
0(
1$
1/
00
01
b11100 2
#29
1!
1&
0"
1'
0#
1(
0$
11
b11101 2
#30
0&
1"
0'
0%
1#
1!
0(
1$
10
01
b11110 2
#31
1%
0!
1&
0"
1'
0#
1(
0$
11
b11111 2
#32
0%
1!
0'
0&
0"
0(
0$
1,
0-
0.
0/
00
01
b100000 2
#33
1$
11
b100001 2
#34
0!
1%
0$
10
01
b100010 2
#35
1$
11
b100011 2
#36
1"
1!
0%
0$
1/
00
01
b100100 2
#37
1$
11
b100101 2
#38
0!
1%
0$
10
01
b100110 2
#39
1$
11
b100111 2
#40
1#
0"
1!
0%
0$
1.
0/
00
01
b101000 2
#41
1$
11
b101001 2
#42
0!
1%
0$
10
01
b101010 2
#43
1$
11
b101011 2
#44
1"
1!
0%
0$
1/
00
01
b101100 2
#45
1$
11
b101101 2
#46
0!
1%
0$
10
01
b101110 2
#47
1$
11
b101111 2
#48
0#
0"
1!
0%
1$
1-
0.
0/
00
01
b110000 2
#49
1#
1(
0$
11
b110001 2
#50
0#
0!
1%
0(
1$
10
01
b110010 2
#51
1#
1(
0$
11
b110011 2
#52
0#
1"
1!
0%
0(
1$
1/
00
01
b110100 2
#53
1#
1(
0$
11
b110101 2
#54
0#
0!
1%
0(
1$
10
01
b110110 2
#55
1#
1(
0$
11
b110111 2
#56
0"
1!
0%
0(
1$
1.
0/
00
01
b111000 2
#57
1"
1'
0#
1(
0$
11
b111001 2
#58
0"
0'
1#
0!
1%
0(
1$
10
01
b111010 2
#59
1"
1'
0#
1(
0$
11
b111011 2
#60
0'
0&
1#
1"
1!
0%
0(
1$
1/
00
01
b111100 2
#61
1%
0!
1&
0"
1'
0#
1(
0$
11
b111101 2
#62
0&
1"
0'
1#
0!
0(
1$
10
01
b111110 2
#63
1!
1&
0"
1'
0#
1(
0$
11
b111111 2
#64
0!
0&
1"
0'
0%
0(
0$
1+
0,
0-
0.
0/
00
01
b1000000 2
#65
1$
11
b1000001 2
#66
1!
0$
10
01
b1000010 2
#67
1$
11
b1000011 2
#68
0"
1&
1!
0$
1/
00
01
b1000100 2
#69
1$
11
b1000101 2
#70
1%
0!
0$
10
01
b1000110 2
#71
1$
11
b1000111 2
#72
0%
1#
1"
0&
0!
0$
1.
0/
00
01
b1001000 2
#73
1$
11
b1001001 2
#74
1!
0$
10
01
b1001010 2
#75
1$
11
b1001011 2
#76
0"
1&
1!
0$
1/
00
01
b1001100 2
#77
1$
11
b1001101 2
#78
1%
0!
0$
10
01
b1001110 2
#79
1$
11
b1001111 2
#80
0%
0#
1"
0&
0!
1$
1-
0.
0/
00
01
b1010000 2
#81
1#
1(
0$
11
b1010001 2
#82
0#
1!
0(
1$
10
01
b1010010 2
#83
1#
1(
0$
11
b1010011 2
#84
0#
0"
1&
1!
0(
1$
1/
00
01
b1010100 2
#85
1#
1(
0$
11
b1010101 2
#86
1%
0#
0!
0(
1$
10
01
b1010110 2
#87
1#
1(
0$
11
b1010111 2
#88
0%
1"
0&
0!
0(
1$
1.
0/
00
01
b1011000 2
#89
1!
1&
0"
1'
0#
1(
0$
11
b1011001 2
#90
0&
1"
0'
0%
1#
1!
0(
1$
10
01
b1011010 2
#91
1%
0!
1&
0"
1'
0#
1(
0$
11
b1011011 2
#92
0'
0%
1#
0"
1!
0(
1$
1/
00
01
b1011100 2
#93
1"
1'
0#
1(
0$
11
b1011101 2
#94
0"
0'
1%
1#
0!
0(
1$
10
01
b1011110 2
#95
1"
1'
0#
1(
0$
11
b1011111 2
#96
0%
1!
0&
0'
1"
0(
0$
1,
0-
0.
0/
00
01
b1100000 2
#97
1$
11
b1100001 2
#98
0!
1%
0$
10
01
b1100010 2
#99
1$
11
b1100011 2
#100
0"
1&
0!
1%
0$
1/
00
01
b1100100 2
#101
1$
11
b1100101 2
#102
1!
0$
10
01
b1100110 2
#103
1$
11
b1100111 2
#104
0%
1#
1"
0&
1!
0$
1.
0/
00
01
b1101000 2
#105
1$
11
b1101001 2
#106
0!
1%
0$
10
01
b1101010 2
#107
1$
11
b1101011 2
#108
0"
1&
0!
1%
0$
1/
00
01
b1101100 2
#109
1$
11
b1101101 2
#110
1!
0$
10
01
b1101110 2
#111
1$
11
b1101111 2
#112
0%
0#
1"
0&
1!
1$
1-
0.
0/
00
01
b1110000 2
#113
1#
1(
0$
11
b1110001 2
#114
0#
0!
1%
0(
1$
10
01
b1110010 2
#115
1#
1(
0$
11
b1110011 2
#116
0#
0"
1&
0!
1%
0(
1$
1/
00
01
b1110100 2
#117
1#
1(
0$
11
b1110101 2
#118
0#
1!
0(
1$
10
01
b1110110 2
#119
1#
1(
0$
11
b1110111 2
#120
0%
1"
0&
1!
0(
1$
1.
0/
00
01
b1111000 2
#121
1%
0!
1&
0"
1'
0#
1(
0$
11
b1111001 2
#122
0&
1"
0'
1#
0!
0(
1$
10
01
b1111010 2
#123
1!
1&
0"
1'
0#
1(
0$
11
b1111011 2
#124
0'
1#
0"
0!
0(
1$
1/
00
01
b1111100 2
#125
1"
1'
0#
1(
0$
11
b1111101 2
#126
0"
0'
1#
1!
0(
1$
10
01
b1111110 2
#127
1"
1'
0#
1(
0$
11
b1111111 2
#128
0"
0'
0!
1#
0&
0%
0(
0$
1*
0+
0,
0-
0.
0/
00
01
b10000000 2
#129
1$
11
b10000001 2
#130
1!
0$
10
01
b10000010 2
#131
1$
11
b10000011 2
#132
1"
0!
0$
1/
00
01
b10000100 2
#133
1$
11
b10000101 2
#134
1!
0$
10
01
b10000110 2
#135
1$
11
b10000111 2
#136
0#
1'
1"
0!
0$
1.
0/
00
01
b10001000 2
#137
1$
11
b10001001 2
#138
1!
0$
10
01
b10001010 2
#139
1$
11
b10001011 2
#140
1&
0"
1!
0$
1/
00
01
b10001100 2
#141
1$
11
b10001101 2
#142
1%
0!
0$
10
01
b10001110 2
#143
1$
11
b10001111 2
#144
0&
0%
1#
0'
0"
0!
1$
1-
0.
0/
00
01
b10010000 2
#145
1"
1'
0#
1(
0$
11
b10010001 2
#146
0"
0'
1#
1!
0(
1$
10
01
b10010010 2
#147
1"
1'
0#
1(
0$
11
b10010011 2
#148
0'
0&
1#
1"
0!
0(
1$
1/
00
01
b10010100 2
#149
1!
1&
0"
1'
0#
1(
0$
11
b10010101 2
#150
0&
1"
0'
0%
1#
1!
0(
1$
10
01
b10010110 2
#151
1%
0!
1&
0"
1'
0#
1(
0$
11
b10010111 2
#152
0&
0%
1"
0!
0(
1$
1.
0/
00
01
b10011000 2
#153
1#
1(
0$
11
b10011001 2
#154
0#
1!
0(
1$
10
01
b10011010 2
#155
1#
1(
0$
11
b10011011 2
#156
1&
0#
0"
1!
0(
1$
1/
00
01
b10011100 2
#157
1#
1(
0$
11
b10011101 2
#158
1%
0#
0!
0(
1$
10
01
b10011110 2
#159
1#
1(
0$
11
b10011111 2
#160
0%
1!
0&
0'
0"
0(
0$
1,
0-
0.
0/
00
01
b10100000 2
#161
1$
11
b10100001 2
#162
0!
1%
0$
10
01
b10100010 2
#163
1$
11
b10100011 2
#164
1"
1!
0%
0$
1/
00
01
b10100100 2
#165
1$
11
b10100101 2
#166
0!
1%
0$
10
01
b10100110 2
#167
1$
11
b10100111 2
#168
0#
1'
1"
1!
0%
0$
1.
0/
00
01
b10101000 2
#169
1$
11
b10101001 2
#170
0!
1%
0$
10
01
b10101010 2
#171
1$
11
b10101011 2
#172
1&
0"
0!
1%
0$
1/
00
01
b10101100 2
#173
1$
11
b10101101 2
#174
1!
0$
10
01
b10101110 2
#175
1$
11
b10101111 2
#176
0%
0&
1#
0'
0"
1!
1$
1-
0.
0/
00
01
b10110000 2
#177
1"
1'
0#
1(
0$
11
b10110001 2
#178
0"
0'
1#
0!
1%
0(
1$
10
01
b10110010 2
#179
1"
1'
0#
1(
0$
11
b10110011 2
#180
0'
0&
1#
1"
1!
0%
0(
1$
1/
00
01
b10110100 2
#181
1%
0!
1&
0"
1'
0#
1(
0$
11
b10110101 2
#182
0&
1"
0'
1#
0!
0(
1$
10
01
b10110110 2
#183
1!
1&
0"
1'
0#
1(
0$
11
b10110111 2
#184
0%
0&
1"
1!
0(
1$
1.
0/
00
01
b10111000 2
#185
1#
1(
0$
11
b10111001 2
#186
0#
0!
1%
0(
1$
10
01
b10111010 2
#187
1#
1(
0$
11
b10111011 2
#188
1&
0#
0"
0!
1%
0(
1$
1/
00
01
b10111100 2
#189
1#
1(
0$
11
b10111101 2
#190
0#
1!
0(
1$
10
01
b10111110 2
#191
1#
1(
0$
11
b10111111 2
#192
0!
0&
1"
0'
0%
0(
0$
1+
0,
0-
0.
0/
00
01
b11000000 2
#193
1$
11
b11000001 2
#194
1!
0$
10
01
b11000010 2
#195
1$
11
b11000011 2
#196
0"
1&
1!
0$
1/
00
01
b11000100 2
#197
1$
11
b11000101 2
#198
1%
0!
0$
10
01
b11000110 2
#199
1$
11
b11000111 2
#200
0%
0#
1'
0"
1&
1!
0$
1.
0/
00
01
b11001000 2
#201
1$
11
b11001001 2
#202
1%
0!
0$
10
01
b11001010 2
#203
1$
11
b11001011 2
#204
0%
1"
1!
0$
1/
00
01
b11001100 2
#205
1$
11
b11001101 2
#206
1%
0!
0$
10
01
b11001110 2
#207
1$
11
b11001111 2
#208
0&
0%
1#
0'
1"
0!
1$
1-
0.
0/
00
01
b11010000 2
#209
1!
1&
0"
1'
0#
1(
0$
11
b11010001 2
#210
0&
1"
0'
0%
1#
1!
0(
1$
10
01
b11010010 2
#211
1%
0!
1&
0"
1'
0#
1(
0$
11
b11010011 2
#212
0'
0%
1#
0"
1!
0(
1$
1/
00
01
b11010100 2
#213
1"
1'
0#
1(
0$
11
b11010101 2
#214
0"
0'
1%
1#
0!
0(
1$
10
01
b11010110 2
#215
1"
1'
0#
1(
0$
11
b11010111 2
#216
0%
0"
1!
0(
1$
1.
0/
00
01
b11011000 2
#217
1#
1(
0$
11
b11011001 2
#218
1%
0#
0!
0(
1$
10
01
b11011010 2
#219
1#
1(
0$
11
b11011011 2
#220
0%
0#
1"
1!
0(
1$
1/
00
01
b11011100 2
#221
1#
1(
0$
11
b11011101 2
#222
1%
0#
0!
0(
1$
10
01
b11011110 2
#223
1#
1(
0$
11
b11011111 2
#224
0%
1!
0&
0'
1"
0(
0$
1,
0-
0.
0/
00
01
b11100000 2
#225
1$
11
b11100001 2
#226
0!
1%
0$
10
01
b11100010 2
#227
1$
11
b11100011 2
#228
0"
1&
0!
1%
0$
1/
00
01
b11100100 2
#229
1$
11
b11100101 2
#230
1!
0$
10
01
b11100110 2
#231
1$
11
b11100111 2
#232
1%
0#
1'
0"
1&
0!
0$
1.
0/
00
01
b11101000 2
#233
1$
11
b11101001 2
#234
1!
0$
10
01
b11101010 2
#235
1$
11
b11101011 2
#236
1"
0!
0$
1/
00
01
b11101100 2
#237
1$
11
b11101101 2
#238
1!
0$
10
01
b11101110 2
#239
1$
11
b11101111 2
#240
0%
0&
1#
0'
1"
1!
1$
1-
0.
0/
00
01
b11110000 2
#241
1%
0!
1&
0"
1'
0#
1(
0$
11
b11110001 2
#242
0&
1"
0'
1#
0!
0(
1$
10
01
b11110010 2
#243
1!
1&
0"
1'
0#
1(
0$
11
b11110011 2
#244
0'
1#
0"
0!
0(
1$
1/
00
01
b11110100 2
#245
1"
1'
0#
1(
0$
11
b11110101 2
#246
0"
0'
1#
1!
0(
1$
10
01
b11110110 2
#247
1"
1'
0#
1(
0$
11
b11110111 2
#248
0"
0!
0(
1$
1.
0/
00
01
b11111000 2
#249
1#
1(
0$
11
b11111001 2
#250
0#
1!
0(
1$
10
01
b11111010 2
#251
1#
1(
0$
11
b11111011 2
#252
0#
1"
0!
0(
1$
1/
00
01
b11111100 2
#253
1#
1(
0$
11
b11111101 2
#254
0#
1!
0(
1$
10
01
b11111110 2
#255
1#
1(
0$
11
b11111111 2
#256
0"
0!
0#
0'
0&
0%
0(
1$
1)
0*
0+
0,
0-
0.
0/
00
01
b100000000 2
#257
1#
1(
0$
11
b100000001 2
#258
0#
1!
0(
1$
10
01
b100000010 2
#259
1#
1(
0$
11
b100000011 2
#260
0#
1"
0!
0(
1$
1/
00
01
b100000100 2
#261
1#
1(
0$
11
b100000101 2
#262
0#
1!
0(
1$
10
01
b100000110 2
#263
1#
1(
0$
11
b100000111 2
#264
0"
0!
0(
1$
1.
0/
00
01
b100001000 2
#265
1"
1'
0#
1(
0$
11
b100001001 2
#266
0"
0'
1#
1!
0(
1$
10
01
b100001010 2
#267
1"
1'
0#
1(
0$
11
b100001011 2
#268
0'
0&
1#
1"
0!
0(
1$
1/
00
01
b100001100 2
#269
1!
1&
0"
1'
0#
1(
0$
11
b100001101 2
#270
0&
1"
0'
0%
1#
1!
0(
1$
10
01
b100001110 2
#271
1%
0!
1&
0"
1'
0#
1(
0$
11
b100001111 2
#272
0'
0&
0%
1#
0"
0!
0$
1-
0.
0/
00
01
b100010000 2
#273
1$
11
b100010001 2
#274
1!
0$
10
01
b100010010 2
#275
1$
11
b100010011 2
#276
1"
0!
0$
1/
00
01
b100010100 2
#277
1$
11
b100010101 2
#278
1!
0$
10
01
b100010110 2
#279
1$
11
b100010111 2
#280
1'
0#
1"
0!
0$
1.
0/
00
01
b100011000 2
#281
1$
11
b100011001 2
#282
1!
0$
10
01
b100011010 2
#283
1$
11
b100011011 2
#284
1&
0"
1!
0$
1/
00
01
b100011100 2
#285
1$
11
b100011101 2
#286
1%
0!
0$
10
01
b100011110 2
#287
1$
11
b100011111 2
#288
0%
1!
0'
0&
0(
0#
0"
1$
1,
0-
0.
0/
00
01
b100100000 2
#289
1#
1(
0$
11
b100100001 2
#290
0#
0!
1%
0(
1$
10
01
b100100010 2
#291
1#
1(
0$
11
b100100011 2
#292
0#
1"
1!
0%
0(
1$
1/
00
01
b100100100 2
#293
1#
1(
0$
11
b100100101 2
#294
0#
0!
1%
0(
1$
10
01
b100100110 2
#295
1#
1(
0$
11
b100100111 2
#296
0"
1!
0%
0(
1$
1.
0/
00
01
b100101000 2
#297
1"
1'
0#
1(
0$
11
b100101001 2
#298
0"
0'
1#
0!
1%
0(
1$
10
01
b100101010 2
#299
1"
1'
0#
1(
0$
11
b100101011 2
#300
0'
0&
1#
1"
1!
0%
0(
1$
1/
00
01
b100101100 2
#301
1%
0!
1&
0"
1'
0#
1(
0$
11
b100101101 2
#302
0&
1"
0'
1#
0!
0(
1$
10
01
b100101110 2
#303
1!
1&
0"
1'
0#
1(
0$
11
b100101111 2
#304
0%
0'
0&
1#
0"
1!
0$
1-
0.
0/
00
01
b100110000 2
#305
1$
11
b100110001 2
#306
0!
1%
0$
10
01
b100110010 2
#307
1$
11
b100110011 2
#308
1"
1!
0%
0$
1/
00
01
b100110100 2
#309
1$
11
b100110101 2
#310
0!
1%
0$
10
01
b100110110 2
#311
1$
11
b100110111 2
#312
1'
0#
1"
1!
0%
0$
1.
0/
00
01
b100111000 2
#313
1$
11
b100111001 2
#314
0!
1%
0$
10
01
b100111010 2
#315
1$
11
b100111011 2
#316
1&
0"
0!
1%
0$
1/
00
01
b100111100 2
#317
1$
11
b100111101 2
#318
1!
0$
10
01
b100111110 2
#319
1$
11
b100111111 2
#320
0!
0&
1"
0'
0(
0#
0%
1$
1+
0,
0-
0.
0/
00
01
b101000000 2
#321
1#
1(
0$
11
b101000001 2
#322
0#
1!
0(
1$
10
01
b101000010 2
#323
1#
1(
0$
11
b101000011 2
#324
0#
0"
1&
1!
0(
1$
1/
00
01
b101000100 2
#325
1#
1(
0$
11
b101000101 2
#326
1%
0#
0!
0(
1$
10
01
b101000110 2
#327
1#
1(
0$
11
b101000111 2
#328
0%
1"
0&
0!
0(
1$
1.
0/
00
01
b101001000 2
#329
1!
1&
0"
1'
0#
1(
0$
11
b101001001 2
#330
0&
1"
0'
0%
1#
1!
0(
1$
10
01
b101001010 2
#331
1%
0!
1&
0"
1'
0#
1(
0$
11
b101001011 2
#332
0'
0%
1#
0"
1!
0(
1$
1/
00
01
b101001100 2
#333
1"
1'
0#
1(
0$
11
b101001101 2
#334
0"
0'
1%
1#
0!
0(
1$
10
01
b101001110 2
#335
1"
1'
0#
1(
0$
11
b101001111 2
#336
0&
0'
0%
1#
1"
0!
0$
1-
0.
0/
00
01
b101010000 2
#337
1$
11
b101010001 2
#338
1!
0$
10
01
b101010010 2
#339
1$
11
b101010011 2
#340
0"
1&
1!
0$
1/
00
01
b101010100 2
#341
1$
11
b101010101 2
#342
1%
0!
0$
10
01
b101010110 2
#343
1$
11
b101010111 2
#344
1'
0%
0#
0"
1&
1!
0$
1.
0/
00
01
b101011000 2
#345
1$
11
b101011001 2
#346
1%
0!
0$
10
01
b101011010 2
#347
1$
11
b101011011 2
#348
0%
1"
1!
0$
1/
00
01
b101011100 2
#349
1$
11
b101011101 2
#350
1%
0!
0$
10
01
b101011110 2
#351
1$
11
b101011111 2
#352
0%
1!
0&
0'
0(
0#
1"
1$
1,
0-
0.
0/
00
01
b101100000 2
#353
1#
1(
0$
11
b101100001 2
#354
0#
0!
1%
0(
1$
10
01
b101100010 2
#355
1#
1(
0$
11
b101100011 2
#356
0#
0"
1&
0!
1%
0(
1$
1/
00
01
b101100100 2
#357
1#
1(
0$
11
b101100101 2
#358
0#
1!
0(
1$
10
01
b101100110 2
#359
1#
1(
0$
11
b101100111 2
#360
0%
1"
0&
1!
0(
1$
1.
0/
00
01
b101101000 2
#361
1%
0!
1&
0"
1'
0#
1(
0$
11
b101101001 2
#362
0&
1"
0'
1#
0!
0(
1$
10
01
b101101010 2
#363
1!
1&
0"
1'
0#
1(
0$
11
b101101011 2
#364
0'
1#
0"
0!
0(
1$
1/
00
01
b101101100 2
#365
1"
1'
0#
1(
0$
11
b101101101 2
#366
0"
0'
1#
1!
0(
1$
10
01
b101101110 2
#367
1"
1'
0#
1(
0$
11
b101101111 2
#368
0%
0&
0'
1#
1"
1!
0$
1-
0.
0/
00
01
b101110000 2
#369
1$
11
b101110001 2
#370
0!
1%
0$
10
01
b101110010 2
#371
1$
11
b101110011 2
#372
0"
1&
0!
1%
0$
1/
00
01
b101110100 2
#373
1$
11
b101110101 2
#374
1!
0$
10
01
b101110110 2
#375
1$
11
b101110111 2
#376
1%
1'
0#
0"
1&
0!
0$
1.
0/
00
01
b101111000 2
#377
1$
11
b101111001 2
#378
1!
0$
10
01
b101111010 2
#379
1$
11
b101111011 2
#380
1"
0!
0$
1/
00
01
b101111100 2
#381
1$
11
b101111101 2
#382
1!
0$
10
01
b101111110 2
#383
1$
11
b101111111 2
#384
0"
0'
1#
0!
0(
0&
0%
1$
1*
0+
0,
0-
0.
0/
00
01
b110000000 2
#385
1"
1'
0#
1(
0$
11
b110000001 2
#386
0"
0'
1#
1!
0(
1$
10
01
b110000010 2
#387
1"
1'
0#
1(
0$
11
b110000011 2
#388
0'
0&
1#
1"
0!
0(
1$
1/
00
01
b110000100 2
#389
1!
1&
0"
1'
0#
1(
0$
11
b110000101 2
#390
0&
1"
0'
0%
1#
1!
0(
1$
10
01
b110000110 2
#391
1%
0!
1&
0"
1'
0#
1(
0$
11
b110000111 2
#392
0&
0%
1"
0!
0(
1$
1.
0/
00
01
b110001000 2
#393
1#
1(
0$
11
b110001001 2
#394
0#
1!
0(
1$
10
01
b110001010 2
#395
1#
1(
0$
11
b110001011 2
#396
1&
0#
0"
1!
0(
1$
1/
00
01
b110001100 2
#397
1#
1(
0$
11
b110001101 2
#398
1%
0#
0!
0(
1$
10
01
b110001110 2
#399
1#
1(
0$
11
b110001111 2
#400
0&
0%
0#
1"
0!
0$
1-
0.
0/
00
01
b110010000 2
#401
1$
11
b110010001 2
#402
1!
0$
10
01
b110010010 2
#403
1$
11
b110010011 2
#404
1&
0"
1!
0$
1/
00
01
b110010100 2
#405
1$
11
b110010101 2
#406
1%
0!
0$
10
01
b110010110 2
#407
1$
11
b110010111 2
#408
0&
0%
1#
1"
0!
0$
1.
0/
00
01
b110011000 2
#409
1$
11
b110011001 2
#410
1!
0$
10
01
b110011010 2
#411
1$
11
b110011011 2
#412
1&
0"
1!
0$
1/
00
01
b110011100 2
#413
1$
11
b110011101 2
#414
1%
0!
0$
10
01
b110011110 2
#415
1$
11
b110011111 2
#416
0%
0'
1!
0&
0(
1#
0"
1$
1,
0-
0.
0/
00
01
b110100000 2
#417
1"
1'
0#
1(
0$
11
b110100001 2
#418
0"
0'
1#
0!
1%
0(
1$
10
01
b110100010 2
#419
1"
1'
0#
1(
0$
11
b110100011 2
#420
0'
0&
1#
1"
1!
0%
0(
1$
1/
00
01
b110100100 2
#421
1%
0!
1&
0"
1'
0#
1(
0$
11
b110100101 2
#422
0&
1"
0'
1#
0!
0(
1$
10
01
b110100110 2
#423
1!
1&
0"
1'
0#
1(
0$
11
b110100111 2
#424
0%
0&
1"
1!
0(
1$
1.
0/
00
01
b110101000 2
#425
1#
1(
0$
11
b110101001 2
#426
0#
0!
1%
0(
1$
10
01
b110101010 2
#427
1#
1(
0$
11
b110101011 2
#428
1&
0#
0"
0!
1%
0(
1$
1/
00
01
b110101100 2
#429
1#
1(
0$
11
b110101101 2
#430
0#
1!
0(
1$
10
01
b110101110 2
#431
1#
1(
0$
11
b110101111 2
#432
0%
0&
0#
1"
1!
0$
1-
0.
0/
00
01
b110110000 2
#433
1$
11
b110110001 2
#434
0!
1%
0$
10
01
b110110010 2
#435
1$
11
b110110011 2
#436
1&
0"
0!
1%
0$
1/
00
01
b110110100 2
#437
1$
11
b110110101 2
#438
1!
0$
10
01
b110110110 2
#439
1$
11
b110110111 2
#440
0%
0&
1#
1"
1!
0$
1.
0/
00
01
b110111000 2
#441
1$
11
b110111001 2
#442
0!
1%
0$
10
01
b110111010 2
#443
1$
11
b110111011 2
#444
1&
0"
0!
1%
0$
1/
00
01
b110111100 2
#445
1$
11
b110111101 2
#446
1!
0$
10
01
b110111110 2
#447
1$
11
b110111111 2
#448
0!
0&
1"
0'
0(
1#
0%
1$
1+
0,
0-
0.
0/
00
01
b111000000 2
#449
1!
1&
0"
1'
0#
1(
0$
11
b111000001 2
#450
0&
1"
0'
0%
1#
1!
0(
1$
10
01
b111000010 2
#451
1%
0!
1&
0"
1'
0#
1(
0$
11
b111000011 2
#452
0'
0%
1#
0"
1!
0(
1$
1/
00
01
b111000100 2
#453
1"
1'
0#
1(
0$
11
b111000101 2
#454
0"
0'
1%
1#
0!
0(
1$
10
01
b111000110 2
#455
1"
1'
0#
1(
0$
11
b111000111 2
#456
0%
0"
1!
0(
1$
1.
0/
00
01
b111001000 2
#457
1#
1(
0$
11
b111001001 2
#458
1%
0#
0!
0(
1$
10
01
b111001010 2
#459
1#
1(
0$
11
b111001011 2
#460
0%
0#
1"
1!
0(
1$
1/
00
01
b111001100 2
#461
1#
1(
0$
11
b111001101 2
#462
1%
0#
0!
0(
1$
10
01
b111001110 2
#463
1#
1(
0$
11
b111001111 2
#464
0%
0#
0"
1!
0$
1-
0.
0/
00
01
b111010000 2
#465
1$
11
b111010001 2
#466
1%
0!
0$
10
01
b111010010 2
#467
1$
11
b111010011 2
#468
0%
1"
1!
0$
1/
00
01
b111010100 2
#469
1$
11
b111010101 2
#470
1%
0!
0$
10
01
b111010110 2
#471
1$
11
b111010111 2
#472
0%
1#
0"
1!
0$
1.
0/
00
01
b111011000 2
#473
1$
11
b111011001 2
#474
1%
0!
0$
10
01
b111011010 2
#475
1$
11
b111011011 2
#476
0%
1"
1!
0$
1/
00
01
b111011100 2
#477
1$
11
b111011101 2
#478
1%
0!
0$
10
01
b111011110 2
#479
1$
11
b111011111 2
#480
0%
1!
0&
0'
0(
1#
1"
1$
1,
0-
0.
0/
00
01
b111100000 2
#481
1%
0!
1&
0"
1'
0#
1(
0$
11
b111100001 2
#482
0&
1"
0'
1#
0!
0(
1$
10
01
b111100010 2
#483
1!
1&
0"
1'
0#
1(
0$
11
b111100011 2
#484
0'
1#
0"
0!
0(
1$
1/
00
01
b111100100 2
#485
1"
1'
0#
1(
0$
11
b111100101 2
#486
0"
0'
1#
1!
0(
1$
10
01
b111100110 2
#487
1"
1'
0#
1(
0$
11
b111100111 2
#488
0"
0!
0(
1$
1.
0/
00
01
b111101000 2
#489
1#
1(
0$
11
b111101001 2
#490
0#
1!
0(
1$
10
01
b111101010 2
#491
1#
1(
0$
11
b111101011 2
#492
0#
1"
0!
0(
1$
1/
00
01
b111101100 2
#493
1#
1(
0$
11
b111101101 2
#494
0#
1!
0(
1$
10
01
b111101110 2
#495
1#
1(
0$
11
b111101111 2
#496
0#
0"
0!
0$
1-
0.
0/
00
01
b111110000 2
#497
1$
11
b111110001 2
#498
1!
0$
10
01
b111110010 2
#499
1$
11
b111110011 2
#500
1"
0!
0$
1/
00
01
b111110100 2
#501
1$
11
b111110101 2
#502
1!
0$
10
01
b111110110 2
#503
1$
11
b111110111 2
#504
1#
0"
0!
0$
1.
0/
00
01
b111111000 2
#505
1$
11
b111111001 2
#506
1!
0$
10
01
b111111010 2
#507
1$
11
b111111011 2
#508
1"
0!
0$
1/
00
01
b111111100 2
#509
1$
11
b111111101 2
