co/verilog/Lab1/Q2/FullAdder.v
module full_adder(
    input A,     // First bit
    input B,     // Second bit
    input Cin,   // Carry-in
    output Sum,  // Sum
    output Cout  // Carry-out
);
    // Logic for Full Adder
    assign Sum = A ^ B ^ Cin;        // XOR for Sum
    assign Cout = ((A ^ B) & Cin) | (A & B); // Carry-out
endmodule

co/verilog/Lab1/Q2/FullAdder_tb.v
`include "FullAdder.v"

module tb_full_adder;
    reg A, B, Cin;         // Inputs
    wire Sum, Cout;        // Outputs

    // Instantiate the Full Adder
    full_adder uut (
        .A(A),
        .B(B),
        .Cin(Cin),
        .Sum(Sum),
        .Cout(Cout)
    );

    // Testbench logic
    initial begin
        $dumpfile("full_adder_tb.vcd");  // Generate waveform file
        $dumpvars(0, tb_full_adder);    // Dump all signals

        // Display Header
        $display("A B Cin | Sum Cout");
        $display("------------------");

        // Iterate through all input combinations
        for (integer i = 0; i < 8; i = i + 1) begin
            {A, B, Cin} = i;           // Assign combinations of A, B, Cin
            #1;                        // Wait for 1 time unit
            $display("%b %b  %b  |  %b   %b", A, B, Cin, Sum, Cout); // Display results
        end

        $finish;  // End simulation
    end
endmodule

co/verilog/Lab1/Q2/full_adder_tb.vcd
$date
	Sat Nov 23 18:34:32 2024
$end
$version
	Icarus Verilog
$end
$timescale
	1s
$end
$scope module tb_full_adder $end
$var wire 1 ! Sum $end
$var wire 1 " Cout $end
$var reg 1 # A $end
$var reg 1 $ B $end
$var reg 1 % Cin $end
$scope module uut $end
$var wire 1 # A $end
$var wire 1 $ B $end
$var wire 1 % Cin $end
$var wire 1 " Cout $end
$var wire 1 ! Sum $end
$upscope $end
$scope begin $ivl_for_loop0 $end
$var integer 32 & i [31:0] $end
$upscope $end
$upscope $end
$enddefinitions $end
$comment Show the parameter values. $end
$dumpall
$end
#0
$dumpvars
b0 &
0%
0$
0#
0"
0!
$end
#1
1!
1%
b1 &
#2
1!
1$
0%
b10 &
#3
1"
0!
1%
b11 &
#4
0"
1!
1#
0$
0%
b100 &
#5
1"
0!
1%
b101 &
#6
0!
1$
0%
b110 &
#7
1!
1%
b111 &
#8
b1000 &
