co/verilog/p2/p2(RF).v
module RegisterFile (
    input [31:0] R_Address,    // 32-bit address to fetch data
    input [31:0] W_Address,    // 32-bit address to store data
    input read_enable,          // Control signal for read operation
    input write_enable,         // Control signal for write operation
    input [7:0] WriteData,      // 8-bit data to write to memory
    output reg [7:0] ReadData   // 8-bit data fetched from memory
);

    // Declare registers to store 4 8-bit bytes
    reg [7:0] register [0:3];    // 4 bytes of memory

    // Initial block to reset registers
    initial begin
        // Reset all register locations to 0
        for (integer i = 0; i < 8; i++) begin
            register[i] = 8'b0;   // Clear all
        end
    end

    // Data Memory Operation (Read/Write Logic)
    always @(*) begin
        if (read_enable) begin
                // Read a byte (8 bits)
                ReadData = {register[R_Address]};
        end else if (write_enable) begin
                // Write a byte (8 bits)
                register[W_Address] = WriteData[7:0];
        end else begin
            ReadData = 8'b0; // Default state (no read or write)
        end
    end

endmodule

co/verilog/p2/p2(RF)_tb.v
`include "p2(RF).v"
`timescale 1ps/1ps

module RegisterFile_tb;

    // Testbench signals
    reg [31:0] R_Address;
    reg [31:0] W_Address;
    reg read_enable;
    reg write_enable;
    reg [7:0] WriteData;
    wire [7:0] ReadData;

    // Instantiate the RegisterFile module
    RegisterFile uut (R_Address, W_Address, read_enable, write_enable, WriteData, ReadData);

    // Test the register file
    initial begin
        $dumpfile("RF_tb.vcd");   
        $dumpvars(0, RegisterFile_tb); 

        // Test case 1: Reset register file
        write_enable = 0; read_enable = 0; R_Address = 32'h0; W_Address = 32'h0;
        #1;

        // Test case 2: Read all registers while empty
        write_enable = 0; read_enable = 1;  R_Address = 32'h0;
        #1;
        write_enable = 0; read_enable = 1;  R_Address = 32'h1;
        #1;
        write_enable = 0; read_enable = 1;  R_Address = 32'h2;
        #1;
        write_enable = 0; read_enable = 1;  R_Address = 32'h3;
        #1;

        // Test case 3: Write data into all registers
        write_enable = 1; read_enable = 0; R_Address = 32'h0; W_Address = 32'h0; WriteData = 8'h1;
        #1;
        write_enable = 1; read_enable = 0; R_Address = 32'h0; W_Address = 32'h1; WriteData = 8'h2;
        #1;
        write_enable = 1; read_enable = 0; R_Address = 32'h0; W_Address = 32'h2; WriteData = 8'h3;
        #1;
        write_enable = 1; read_enable = 0; R_Address = 32'h0; W_Address = 32'h3; WriteData = 8'h4;
        #1;

        // Test case 4: Read all registers while full
        write_enable = 0; read_enable = 1;  R_Address = 32'h0;
        #1;
        write_enable = 0; read_enable = 1;  R_Address = 32'h1;
        #1;
        write_enable = 0; read_enable = 1;  R_Address = 32'h2;
        #1;
        write_enable = 0; read_enable = 1;  R_Address = 32'h3;
        #1;
 
        // Finish the simulation
        $finish;
    end

    // Monitor outputs
    initial begin
        $monitor("Time: %0t | R_Address: %h | W_Address: %h | WriteData: %h | ReadData: %h | read_enable: %b | write_enable: %b |",
                 $time, R_Address, W_Address, WriteData, ReadData, read_enable, write_enable);
    end

endmodule

co/verilog/p2/RF_tb.vcd
$date
	Fri Dec 20 15:51:07 2024
$end
$version
	Icarus Verilog
$end
$timescale
	1ps
$end
$scope module RegisterFile_tb $end
$var wire 8 ! ReadData [7:0] $end
$var reg 32 " R_Address [31:0] $end
$var reg 32 # W_Address [31:0] $end
$var reg 8 $ WriteData [7:0] $end
$var reg 1 % read_enable $end
$var reg 1 & write_enable $end
$scope module uut $end
$var wire 32 ' R_Address [31:0] $end
$var wire 32 ( W_Address [31:0] $end
$var wire 8 ) WriteData [7:0] $end
$var wire 1 % read_enable $end
$var wire 1 & write_enable $end
$var reg 8 * ReadData [7:0] $end
$scope begin $ivl_for_loop0 $end
$var integer 32 + i [31:0] $end
$upscope $end
$upscope $end
$upscope $end
$enddefinitions $end
$comment Show the parameter values. $end
$dumpall
$end
#0
$dumpvars
b1000 +
b0 *
bx )
b0 (
b0 '
0&
0%
bx $
b0 #
b0 "
b0 !
$end
#1
1%
#2
b1 "
b1 '
#3
b10 "
b10 '
#4
b11 "
b11 '
#5
b1 $
b1 )
b0 "
b0 '
0%
1&
#6
b10 $
b10 )
b1 #
b1 (
#7
b11 $
b11 )
b10 #
b10 (
#8
b100 $
b100 )
b11 #
b11 (
#9
b1 !
b1 *
1%
0&
#10
b10 !
b10 *
b1 "
b1 '
#11
b11 !
b11 *
b10 "
b10 '
#12
b100 !
b100 *
b11 "
b11 '
