co/verilog/Lab1/Q3/MUX4X1/MUX4X1.v
module mux_4x1 (
    input A,          // Input 1
    input B,          // Input 2
    input C,          // Input 3
    input D,          // Input 4
    input [1:0] Sel,  // 2-bit Select line
    output reg Y      // Output
);

/*
    // Assign output based on Sel
    assign Y = (Sel == 2'b00) ? A :
               (Sel == 2'b01) ? B :
               (Sel == 2'b10) ? C :
                                D;
*/
    always @(*) begin
        if (Sel == 2'b00)
            Y = A;    // Select A when Sel is 00
        else if (Sel == 2'b01)
            Y = B;    // Select B when Sel is 01
        else if (Sel == 2'b10)
            Y = C;    // Select C when Sel is 10
        else
            Y = D;    // Select D when Sel is 11
    end
endmodule

co/verilog/Lab1/Q3/MUX4X1/MUX4X1_tb.v
`include "MUX4X1.v"

module tb_mux_4x1;

    reg A, B, C, D;
    reg [1:0] Sel;
    wire Y;

    // Instantiate the 4x1 MUX
    mux_4x1 uut (
        .A(A),
        .B(B),
        .C(C),
        .D(D),
        .Sel(Sel),
        .Y(Y)
    );

    initial begin
        $dumpfile("mux_4x1_tb.vcd");  // VCD file for waveform
        $dumpvars(0, tb_mux_4x1);

        $display("4x1 MUX Truth Table:");
        $display("A B C D Sel | Y");
        $display("-----------------");
        for (integer i = 0; i < 64; i = i + 1) begin
            {A, B, C, D, Sel} = i; // Generate all combinations
            #1;                   // Wait for simulation step
            $display("%b %b %b %b %b  | %b", A, B, C, D, Sel, Y);
        end

        $finish;
    end
endmodule

co/verilog/Lab1/Q3/MUX4X1/mux_4x1_tb.vcd
$date
	Sat Nov 23 18:55:20 2024
$end
$version
	Icarus Verilog
$end
$timescale
	1s
$end
$scope module tb_mux_4x1 $end
$var wire 1 ! Y $end
$var reg 1 " A $end
$var reg 1 # B $end
$var reg 1 $ C $end
$var reg 1 % D $end
$var reg 2 & Sel [1:0] $end
$scope module uut $end
$var wire 1 " A $end
$var wire 1 # B $end
$var wire 1 $ C $end
$var wire 1 % D $end
$var wire 2 ' Sel [1:0] $end
$var reg 1 ! Y $end
$upscope $end
$scope begin $ivl_for_loop0 $end
$var integer 32 ( i [31:0] $end
$upscope $end
$upscope $end
$enddefinitions $end
$comment Show the parameter values. $end
$dumpall
$end
#0
$dumpvars
b0 (
b0 '
b0 &
0%
0$
0#
0"
0!
$end
#1
b1 &
b1 '
b1 (
#2
b10 &
b10 '
b10 (
#3
b11 &
b11 '
b11 (
#4
1%
b0 &
b0 '
b100 (
#5
b1 &
b1 '
b101 (
#6
b10 &
b10 '
b110 (
#7
1!
b11 &
b11 '
b111 (
#8
0!
1$
0%
b0 &
b0 '
b1000 (
#9
b1 &
b1 '
b1001 (
#10
1!
b10 &
b10 '
b1010 (
#11
0!
b11 &
b11 '
b1011 (
#12
1%
b0 &
b0 '
b1100 (
#13
b1 &
b1 '
b1101 (
#14
1!
b10 &
b10 '
b1110 (
#15
b11 &
b11 '
b1111 (
#16
0!
1#
0$
0%
b0 &
b0 '
b10000 (
#17
1!
b1 &
b1 '
b10001 (
#18
0!
b10 &
b10 '
b10010 (
#19
b11 &
b11 '
b10011 (
#20
1%
b0 &
b0 '
b10100 (
#21
1!
b1 &
b1 '
b10101 (
#22
0!
b10 &
b10 '
b10110 (
#23
1!
b11 &
b11 '
b10111 (
#24
0!
1$
0%
b0 &
b0 '
b11000 (
#25
1!
b1 &
b1 '
b11001 (
#26
b10 &
b10 '
b11010 (
#27
0!
b11 &
b11 '
b11011 (
#28
1%
b0 &
b0 '
b11100 (
#29
1!
b1 &
b1 '
b11101 (
#30
b10 &
b10 '
b11110 (
#31
b11 &
b11 '
b11111 (
#32
1"
0#
0$
0%
b0 &
b0 '
b100000 (
#33
0!
b1 &
b1 '
b100001 (
#34
b10 &
b10 '
b100010 (
#35
b11 &
b11 '
b100011 (
#36
1!
1%
b0 &
b0 '
b100100 (
#37
0!
b1 &
b1 '
b100101 (
#38
b10 &
b10 '
b100110 (
#39
1!
b11 &
b11 '
b100111 (
#40
1$
0%
b0 &
b0 '
b101000 (
#41
0!
b1 &
b1 '
b101001 (
#42
1!
b10 &
b10 '
b101010 (
#43
0!
b11 &
b11 '
b101011 (
#44
1!
1%
b0 &
b0 '
b101100 (
#45
0!
b1 &
b1 '
b101101 (
#46
1!
b10 &
b10 '
b101110 (
#47
b11 &
b11 '
b101111 (
#48
1#
0$
0%
b0 &
b0 '
b110000 (
#49
b1 &
b1 '
b110001 (
#50
0!
b10 &
b10 '
b110010 (
#51
b11 &
b11 '
b110011 (
#52
1!
1%
b0 &
b0 '
b110100 (
#53
b1 &
b1 '
b110101 (
#54
0!
b10 &
b10 '
b110110 (
#55
1!
b11 &
b11 '
b110111 (
#56
1$
0%
b0 &
b0 '
b111000 (
#57
b1 &
b1 '
b111001 (
#58
b10 &
b10 '
b111010 (
#59
0!
b11 &
b11 '
b111011 (
#60
1!
1%
b0 &
b0 '
b111100 (
#61
b1 &
b1 '
b111101 (
#62
b10 &
b10 '
b111110 (
#63
b11 &
b11 '
b111111 (
#64
b1000000 (
