co/verilog/Lab1/Q1/Question1.v
/*
Implementation of simple combinational circuit
*/

module ComCir1 (input A, B, C, D, E,output Y);
/*  input A, B, C, D, E;
    output Y;
    wire w1, w2, w3, w4;*/
 /*   
    // Gate instantiations (STRUCTURAL)
    or o1(w1, A, B);        // OR gate o1: w1 = A | B
    not n1(w3, w1);         // NOT gate n1: w3 = ~w1
    and a1(w2, C, D);       // AND gate a1: w2 = C & D
    or o2(w4, w3, w2);      // OR gate o2: w4 = w3 | w2
    and a2(Y, w4, E);       // AND gate a2: Y = w4 & E
*/
/*  (BEHAVIORAL)
    assign w1 = A | B;
    assign w2 = C & D;
    assign w3 = ~w1;
    assign w4 = w3 | w2;
    assign Y = E & w4;*/

    assign Y = ( ( (~(A | B)) | (C & D) ) & E); 
    

endmodule

co/verilog/Lab1/Q1/Question1_tb.v
/*
Implementation of test bench of 
simple combinational circuit
*/
`include "Question1.v"

module Qustion1_tb;
    reg A, B, C, D, E; // Inputs
    wire Y; // Output
    
   // ComCir1 Comb1(A, B, C, D, E, Y);
    //uut -> unit under test
    ComCir1 uut (
    .A(A), 
    .B(B), 
    .C(C), 
    .D(D), 
    .E(E), 
    .Y(Y)
);


// Test the circuit
    initial begin

        $dumpfile("Question1_tb.vcd");   // VCD stands for Value Change Dump, which is a file format that stores the values of signals 
        $dumpvars(0, Qustion1_tb); // Dump all signals in tb_combinational_circuit and The 0 means dump everything

        // Monitor the inputs and output
        $monitor("Time=%0t | A=%b, B=%b, C=%b, D=%b, E=%b | Y=%b", $time, A, B, C, D, E, Y);

        // Test all combinations of inputs
        for (integer i = 0; i < 32; i++) begin
            {A, B, C, D, E} = i; // Assign input combinations
            #1;                // Wait for 1 time units
        end

        $finish; // End the simulation
    end
endmodule

co/verilog/Lab1/Q1/Question1_tb.vcd
$date
	Sat Nov 23 18:27:14 2024
$end
$version
	Icarus Verilog
$end
$timescale
	1s
$end
$scope module Qustion1_tb $end
$var wire 1 ! Y $end
$var reg 1 " A $end
$var reg 1 # B $end
$var reg 1 $ C $end
$var reg 1 % D $end
$var reg 1 & E $end
$scope module uut $end
$var wire 1 " A $end
$var wire 1 # B $end
$var wire 1 $ C $end
$var wire 1 % D $end
$var wire 1 & E $end
$var wire 1 ! Y $end
$upscope $end
$scope begin $ivl_for_loop0 $end
$var integer 32 ' i [31:0] $end
$upscope $end
$upscope $end
$enddefinitions $end
$comment Show the parameter values. $end
$dumpall
$end
#0
$dumpvars
b0 '
0&
0%
0$
0#
0"
0!
$end
#1
1!
1&
b1 '
#2
0!
1%
0&
b10 '
#3
1!
1&
b11 '
#4
0!
1$
0%
0&
b100 '
#5
1!
1&
b101 '
#6
0!
1%
0&
b110 '
#7
1!
1&
b111 '
#8
0!
1#
0$
0%
0&
b1000 '
#9
1&
b1001 '
#10
1%
0&
b1010 '
#11
1&
b1011 '
#12
1$
0%
0&
b1100 '
#13
1&
b1101 '
#14
1%
0&
b1110 '
#15
1!
1&
b1111 '
#16
0!
1"
0#
0$
0%
0&
b10000 '
#17
1&
b10001 '
#18
1%
0&
b10010 '
#19
1&
b10011 '
#20
1$
0%
0&
b10100 '
#21
1&
b10101 '
#22
1%
0&
b10110 '
#23
1!
1&
b10111 '
#24
0!
1#
0$
0%
0&
b11000 '
#25
1&
b11001 '
#26
1%
0&
b11010 '
#27
1&
b11011 '
#28
1$
0%
0&
b11100 '
#29
1&
b11101 '
#30
1%
0&
b11110 '
#31
1!
1&
b11111 '
#32
b100000 '
